mdorado/__init__.py
mdorado/correlations.py
mdorado/gofr.py
mdorado/hb_analyze.py
mdorado/lifetime.py
mdorado/msd.py
mdorado/veccor.py
mdorado/data/.water.xtc_offsets.npz
mdorado/data/anisolg2.dat
mdorado/data/datafilenames.py
mdorado/data/fast_isolg1.dat
mdorado/data/fast_isolg2.dat
mdorado/data/getnvec_42.dat
mdorado/data/getvec_42.dat
mdorado/data/gofr_cc.dat
mdorado/data/gofr_sc.dat
mdorado/data/gofr_ss.dat
mdorado/data/hb_analyze.dat
mdorado/data/lifetime_test.dat
mdorado/data/msd_h.dat
mdorado/data/msd_molpos.npy
mdorado/data/slow_isolg2.dat
mdorado/data/vectors_isocorrel.npy
mdorado/data/water.tpr
mdorado/data/water.xtc
mdorado-0.2.1.dist-info/LICENSE
mdorado-0.2.1.dist-info/METADATA
mdorado-0.2.1.dist-info/WHEEL
mdorado-0.2.1.dist-info/top_level.txt
mdorado-0.2.1.dist-info/RECORD
